arcade_math/__init__.py
arcade_math/tools/__init__.py
arcade_math/tools/arithmetic.py
arcade_math/tools/exponents.py
arcade_math/tools/miscellaneous.py
arcade_math/tools/random.py
arcade_math/tools/rational.py
arcade_math/tools/rounding.py
arcade_math/tools/statistics.py
arcade_math/tools/trigonometry.py
arcade_math-2.0.2.dist-info/METADATA
arcade_math-2.0.2.dist-info/WHEEL
arcade_math-2.0.2.dist-info/licenses/LICENSE
arcade_math-2.0.2.dist-info/RECORD
